cdfutils/Config.py
cdfutils/Textfile.py
cdfutils/__init__.py
cdfutils/DotNet/Dialogs.py
cdfutils/DotNet/Menus.py
cdfutils/DotNet/__init__.py
cdfutils-1.1.2.dist-info/licenses/LICENSE.txt
cdfutils-1.1.2.dist-info/METADATA
cdfutils-1.1.2.dist-info/WHEEL
cdfutils-1.1.2.dist-info/top_level.txt
cdfutils-1.1.2.dist-info/RECORD
