Metadata-Version: 2.4
Name: cdfutils
Version: 1.1.2
Summary: A general utility library of miscellaneous functions and classes
Home-page: https://github.com/cdfarrow/cdfutils/wiki
Author: Craig Farrow
License: "GPL-2.0-or-later"
Platform: Windows
Platform: Linux
Classifier: Intended Audience :: Developers
Classifier: Programming Language :: Python :: 3
Classifier: Programming Language :: Python :: 3.6
Classifier: Programming Language :: Python :: 3.7
Classifier: Programming Language :: Python :: 3.8
Classifier: Programming Language :: Python :: 3.9
Classifier: Programming Language :: Python :: 3.10
Classifier: Programming Language :: Python :: 3.11
Classifier: Programming Language :: Python :: 3.12
Classifier: Programming Language :: Python :: 3.13
Requires-Python: >=3.6
License-File: LICENSE.txt
Dynamic: license-file
